{
    "name": "MainPage",
    "fields": [
        {
            "fieldName": "content",
            "fieldType": "byte[]",
            "fieldTypeBlobContent": "text",
            "fieldValidateRules": [
                "required"
            ]
        },
        {
            "fieldName": "motto",
            "fieldType": "String",
            "fieldValidateRules": [
                "required"
            ]
        }
    ],
    "relationships": [
        {
            "relationshipType": "one-to-many",
            "otherEntityName": "contact",
            "otherEntityRelationshipName": "mainPage",
            "relationshipName": "contacts"
        }
    ],
    "changelogDate": "20191010144448",
    "entityTableName": "main_page",
    "dto": "no",
    "pagination": "no",
    "service": "no",
    "jpaMetamodelFiltering": false,
    "fluentMethods": true,
    "clientRootFolder": "",
    "applications": "*"
}